problems/custom_uart/clk_strobe.v
/**
 *  Generates strobe for clk/DIVISOR.
 */
module clk_strobe #(parameter DIVISOR = 4)(
    input clk,
    input reset,

    output strobe
);

reg [31:0]counter = 0;
assign strobe = (counter == DIVISOR - 1);

always @(posedge clk) begin
    if (!reset || counter == DIVISOR - 1)
        counter <= 0;
    else
        counter <= counter + 1;
end

endmodule

problems/custom_uart/uart_rx.v
module uart_rx #(
    parameter FREQ = 1e9,
    parameter BAUD = 115200,
    parameter DATA_SIZE = 8
)(
    input clk,
    input in,

    output reg [DATA_SIZE-1:0]data,
    output reg is_receiving,
    output reg is_completed
);

localparam S_IDLE = 0;
localparam S_RECV = 1;
localparam S_STOP = 2;

initial begin
    data = 0;
    is_receiving = 0;
    is_completed = 0;
end

// 0 -- reset enabled, 1 -- disabled.
reg reset = 1'b0;
reg [3:0] state = S_IDLE;

// RX strobe
wire strobe;
clk_strobe #(.DIVISOR(FREQ/BAUD)) clk_strobe(
    .clk(clk),
    .reset(reset),
    .strobe(strobe)
);

reg [7:0]current_bit = 0;
always @(posedge clk) begin
    case (state)
        S_IDLE:
            if (in == 0) begin
                state <= S_RECV;
                is_receiving <= 1;
                is_completed <= 0;
                reset <= 1'b1;          // disable reset
                data <= 0;              // reset output data
                current_bit <= 0;       // reset counter
            end
        S_RECV:
            if (strobe) begin
                if (current_bit != DATA_SIZE) begin
                    // FIXME: Maybe we should buffer received data to increase
                    //        time to read output data when is_completed == 1.
                    data[current_bit] <= in;          // receive bit
                    current_bit <= current_bit + 1;
                end
                else begin
                    state <= S_STOP;
                    is_completed <= 1;
                end
            end
        S_STOP:
            if (strobe) begin
                state <= S_IDLE;
                is_receiving <= 0;
                reset <= 0;
            end
    endcase
end

endmodule

problems/custom_uart/uart_tx.v
module uart_tx #(
    parameter FREQ = 1e9,
    parameter BAUD = 115200,
    parameter DATA_SIZE = 8
)(
    input clk,
    input start,
    input [DATA_SIZE-1:0]data,

    output reg out
);

localparam TX_IDLE = 0;
localparam TX_SEND = 1;
localparam TX_STOP = 2;

initial begin
    out = 1;
end

// 0 -- reset enabled, 1 -- disabled.
reg reset = 1'b0;
reg [3:0] state = TX_IDLE;

// TX strobe
wire tx_strobe;
clk_strobe #(.DIVISOR(FREQ/BAUD)) clk_strobe(
    .clk(clk),
    .reset(reset),
    .strobe(tx_strobe)
);

reg [DATA_SIZE-1:0]buffer = 0;
reg [7:0]current_bit = 0;
always @(posedge clk) begin
    case (state)
        TX_IDLE:
            if (start) begin
                state <= TX_SEND;
                reset <= 1'b1;          // disable reset
                buffer <= data;         // buffer data for sending
                current_bit <= 0;       // reset counter
                out <= 1'b0;            // output start bit
            end
        TX_SEND:
            if (tx_strobe) begin
                if (current_bit != DATA_SIZE) begin
                    out <= buffer[0];                               // send data bit
                    buffer <= {1'b0, buffer[DATA_SIZE-1:1]};        // shift data in buffer
                    current_bit <= current_bit + 1;
                end
                else begin
                    out <= 1'b1;                        // output stop bit
                    state <= TX_STOP;
                end
            end
        // NOTE: Losing one clk cycle if sending is continous (transition
        //       TX_STOP -> TX_IDLE -> TX_SEND).
        //       1) If this module will use some output reg to show ready for
        //       next sending, it will be ok.
        //       2) Otherwise can be fixed with direct transition TX_STOP ->
        //       TX_SEND.
        TX_STOP:
            if (tx_strobe) begin
                state <= TX_IDLE;
                reset <= 1'b0;          // enable reset
            end
    endcase
end

endmodule

problems/custom_uart/testbench.v
`timescale 1 ns / 100 ps

module testbench;

reg clk = 1'b0;

always begin
    #1 clk = ~clk;
end

localparam DATA_SIZE = 5;

reg [DATA_SIZE-1:0]tx_data = 0;
reg tx_start = 0;
wire tx_output;
uart_tx #(
    .FREQ(100),
    .BAUD(25),
    .DATA_SIZE(DATA_SIZE)
) uart_tx (
    .clk(clk),
    .start(tx_start),
    .data(tx_data),
    .out(tx_out)
);

wire [DATA_SIZE-1:0]rx_data;
wire rx_is_receiving;
wire rx_is_completed;
uart_rx #(
    .FREQ(100),
    .BAUD(25),
    .DATA_SIZE(DATA_SIZE)
) uart_rx (
    .clk(clk),
    .in(tx_out),
    .data(rx_data),
    .is_receiving(rx_is_receiving),
    .is_completed(rx_is_completed)
);

initial begin
    $dumpvars;
    #2
//    tx_data = 8'h55;
    tx_data = 8'hD;
    tx_start = 1'b1;
    #2
    tx_data = 0;
    tx_start = 0;
    #96
    tx_data = 8'h0;
    tx_start = 1'b1;

    #200 $finish;
end

endmodule

problems/custom_uart/dump.vcd
$date
	Mon Apr 29 21:55:50 2024
$end
$version
	Icarus Verilog
$end
$timescale
	100ps
$end
$scope module testbench $end
$var wire 1 ! tx_out $end
$var wire 1 " rx_is_receiving $end
$var wire 1 # rx_is_completed $end
$var wire 5 $ rx_data [4:0] $end
$var parameter 32 % DATA_SIZE $end
$var reg 1 & clk $end
$var reg 5 ' tx_data [4:0] $end
$var reg 1 ( tx_start $end
$scope module uart_rx $end
$var wire 1 & clk $end
$var wire 1 ) strobe $end
$var wire 1 ! in $end
$var parameter 32 * BAUD $end
$var parameter 32 + DATA_SIZE $end
$var parameter 32 , FREQ $end
$var parameter 32 - S_IDLE $end
$var parameter 32 . S_RECV $end
$var parameter 32 / S_STOP $end
$var reg 8 0 current_bit [7:0] $end
$var reg 5 1 data [4:0] $end
$var reg 1 # is_completed $end
$var reg 1 " is_receiving $end
$var reg 1 2 reset $end
$var reg 4 3 state [3:0] $end
$scope module clk_strobe $end
$var wire 1 & clk $end
$var wire 1 2 reset $end
$var wire 1 ) strobe $end
$var parameter 32 4 DIVISOR $end
$var reg 32 5 counter [31:0] $end
$upscope $end
$upscope $end
$scope module uart_tx $end
$var wire 1 & clk $end
$var wire 5 6 data [4:0] $end
$var wire 1 ( start $end
$var wire 1 7 tx_strobe $end
$var parameter 32 8 BAUD $end
$var parameter 32 9 DATA_SIZE $end
$var parameter 32 : FREQ $end
$var parameter 32 ; TX_IDLE $end
$var parameter 32 < TX_SEND $end
$var parameter 32 = TX_STOP $end
$var reg 5 > buffer [4:0] $end
$var reg 8 ? current_bit [7:0] $end
$var reg 1 ! out $end
$var reg 1 @ reset $end
$var reg 4 A state [3:0] $end
$scope module clk_strobe $end
$var wire 1 & clk $end
$var wire 1 @ reset $end
$var wire 1 7 strobe $end
$var parameter 32 B DIVISOR $end
$var reg 32 C counter [31:0] $end
$upscope $end
$upscope $end
$upscope $end
$enddefinitions $end
$comment Show the parameter values. $end
$dumpall
b100 B
b10 =
b1 <
b0 ;
b1100100 :
b101 9
b11001 8
b100 4
b10 /
b1 .
b0 -
b1100100 ,
b101 +
b11001 *
b101 %
$end
#0
$dumpvars
b0 C
b0 A
0@
b0 ?
b0 >
07
b0 6
b0 5
b0 3
02
b0 1
b0 0
0)
0(
b0 '
0&
b0 $
0#
0"
1!
$end
#10
1&
#20
0&
1(
b1101 '
b1101 6
#30
0!
b1101 >
1@
b1 A
1&
#40
0&
0(
b0 '
b0 6
#50
b1 C
12
1"
b1 3
1&
#60
0&
#70
b1 5
b10 C
1&
#80
0&
#90
17
b11 C
b10 5
1&
#100
0&
#110
1)
b11 5
b1 ?
b110 >
1!
07
b0 C
1&
#120
0&
#130
b1 C
0)
b0 5
b1 0
b1 $
b1 1
1&
#140
0&
#150
b1 5
b10 C
1&
#160
0&
#170
17
b11 C
b10 5
1&
#180
0&
#190
1)
b11 5
b10 ?
b11 >
0!
07
b0 C
1&
#200
0&
#210
b1 C
0)
b0 5
b10 0
1&
#220
0&
#230
b1 5
b10 C
1&
#240
0&
#250
17
b11 C
b10 5
1&
#260
0&
#270
1)
b11 5
b11 ?
b1 >
1!
07
b0 C
1&
#280
0&
#290
b1 C
0)
b0 5
b11 0
b101 $
b101 1
1&
#300
0&
#310
b1 5
b10 C
1&
#320
0&
#330
17
b11 C
b10 5
1&
#340
0&
#350
1)
b11 5
b100 ?
b0 >
07
b0 C
1&
#360
0&
#370
b1 C
0)
b0 5
b100 0
b1101 $
b1101 1
1&
#380
0&
#390
b1 5
b10 C
1&
#400
0&
#410
17
b11 C
b10 5
1&
#420
0&
#430
1)
b11 5
b101 ?
0!
07
b0 C
1&
#440
0&
#450
b1 C
0)
b0 5
b101 0
1&
#460
0&
#470
b1 5
b10 C
1&
#480
0&
#490
17
b11 C
b10 5
1&
#500
0&
#510
1)
b11 5
b10 A
1!
07
b0 C
1&
#520
0&
#530
b1 C
0)
b0 5
1#
b10 3
1&
#540
0&
#550
b1 5
b10 C
1&
#560
0&
#570
17
b11 C
b10 5
1&
#580
0&
#590
1)
b11 5
0@
b0 A
07
b0 C
1&
#600
0&
#610
0)
b0 5
02
0"
b0 3
1&
#620
0&
#630
1&
#640
0&
#650
1&
#660
0&
#670
1&
#680
0&
#690
1&
#700
0&
#710
1&
#720
0&
#730
1&
#740
0&
#750
1&
#760
0&
#770
1&
#780
0&
#790
1&
#800
0&
#810
1&
#820
0&
#830
1&
#840
0&
#850
1&
#860
0&
#870
1&
#880
0&
#890
1&
#900
0&
#910
1&
#920
0&
#930
1&
#940
0&
#950
1&
#960
0&
#970
1&
#980
0&
#990
1&
#1000
0&
1(
#1010
0!
b0 ?
1@
b1 A
1&
#1020
0&
#1030
b0 0
b0 $
b0 1
12
0#
1"
b1 3
b1 C
1&
#1040
0&
#1050
b10 C
b1 5
1&
#1060
0&
#1070
b10 5
17
b11 C
1&
#1080
0&
#1090
07
b0 C
b1 ?
1)
b11 5
1&
#1100
0&
#1110
b1 0
0)
b0 5
b1 C
1&
#1120
0&
#1130
b10 C
b1 5
1&
#1140
0&
#1150
b10 5
17
b11 C
1&
#1160
0&
#1170
07
b0 C
b10 ?
1)
b11 5
1&
#1180
0&
#1190
b10 0
0)
b0 5
b1 C
1&
#1200
0&
#1210
b10 C
b1 5
1&
#1220
0&
#1230
b10 5
17
b11 C
1&
#1240
0&
#1250
07
b0 C
b11 ?
1)
b11 5
1&
#1260
0&
#1270
b11 0
0)
b0 5
b1 C
1&
#1280
0&
#1290
b10 C
b1 5
1&
#1300
0&
#1310
b10 5
17
b11 C
1&
#1320
0&
#1330
07
b0 C
b100 ?
1)
b11 5
1&
#1340
0&
#1350
b100 0
0)
b0 5
b1 C
1&
#1360
0&
#1370
b10 C
b1 5
1&
#1380
0&
#1390
b10 5
17
b11 C
1&
#1400
0&
#1410
07
b0 C
b101 ?
1)
b11 5
1&
#1420
0&
#1430
b101 0
0)
b0 5
b1 C
1&
#1440
0&
#1450
b10 C
b1 5
1&
#1460
0&
#1470
b10 5
17
b11 C
1&
#1480
0&
#1490
07
b0 C
b10 A
1!
1)
b11 5
1&
#1500
0&
#1510
1#
b10 3
0)
b0 5
b1 C
1&
#1520
0&
#1530
b10 C
b1 5
1&
#1540
0&
#1550
b10 5
17
b11 C
1&
#1560
0&
#1570
07
b0 C
0@
b0 A
1)
b11 5
1&
#1580
0&
#1590
02
0"
b0 3
0)
b0 5
0!
b0 ?
1@
b1 A
1&
#1600
0&
#1610
b1 C
b0 0
12
0#
1"
b1 3
1&
#1620
0&
#1630
b1 5
b10 C
1&
#1640
0&
#1650
17
b11 C
b10 5
1&
#1660
0&
#1670
1)
b11 5
b1 ?
07
b0 C
1&
#1680
0&
#1690
b1 C
0)
b0 5
b1 0
1&
#1700
0&
#1710
b1 5
b10 C
1&
#1720
0&
#1730
17
b11 C
b10 5
1&
#1740
0&
#1750
1)
b11 5
b10 ?
07
b0 C
1&
#1760
0&
#1770
b1 C
0)
b0 5
b10 0
1&
#1780
0&
#1790
b1 5
b10 C
1&
#1800
0&
#1810
17
b11 C
b10 5
1&
#1820
0&
#1830
1)
b11 5
b11 ?
07
b0 C
1&
#1840
0&
#1850
b1 C
0)
b0 5
b11 0
1&
#1860
0&
#1870
b1 5
b10 C
1&
#1880
0&
#1890
17
b11 C
b10 5
1&
#1900
0&
#1910
1)
b11 5
b100 ?
07
b0 C
1&
#1920
0&
#1930
b1 C
0)
b0 5
b100 0
1&
#1940
0&
#1950
b1 5
b10 C
1&
#1960
0&
#1970
17
b11 C
b10 5
1&
#1980
0&
#1990
1)
b11 5
b101 ?
07
b0 C
1&
#2000
0&
#2010
b1 C
0)
b0 5
b101 0
1&
#2020
0&
#2030
b1 5
b10 C
1&
#2040
0&
#2050
17
b11 C
b10 5
1&
#2060
0&
#2070
1)
b11 5
b10 A
1!
07
b0 C
1&
#2080
0&
#2090
b1 C
0)
b0 5
1#
b10 3
1&
#2100
0&
#2110
b1 5
b10 C
1&
#2120
0&
#2130
17
b11 C
b10 5
1&
#2140
0&
#2150
1)
b11 5
0@
b0 A
07
b0 C
1&
#2160
0&
#2170
0!
b0 ?
1@
b1 A
0)
b0 5
02
0"
b0 3
1&
#2180
0&
#2190
b0 0
12
0#
1"
b1 3
b1 C
1&
#2200
0&
#2210
b10 C
b1 5
1&
#2220
0&
#2230
b10 5
17
b11 C
1&
#2240
0&
#2250
07
b0 C
b1 ?
1)
b11 5
1&
#2260
0&
#2270
b1 0
0)
b0 5
b1 C
1&
#2280
0&
#2290
b10 C
b1 5
1&
#2300
0&
#2310
b10 5
17
b11 C
1&
#2320
0&
#2330
07
b0 C
b10 ?
1)
b11 5
1&
#2340
0&
#2350
b10 0
0)
b0 5
b1 C
1&
#2360
0&
#2370
b10 C
b1 5
1&
#2380
0&
#2390
b10 5
17
b11 C
1&
#2400
0&
#2410
07
b0 C
b11 ?
1)
b11 5
1&
#2420
0&
#2430
b11 0
0)
b0 5
b1 C
1&
#2440
0&
#2450
b10 C
b1 5
1&
#2460
0&
#2470
b10 5
17
b11 C
1&
#2480
0&
#2490
07
b0 C
b100 ?
1)
b11 5
1&
#2500
0&
#2510
b100 0
0)
b0 5
b1 C
1&
#2520
0&
#2530
b10 C
b1 5
1&
#2540
0&
#2550
b10 5
17
b11 C
1&
#2560
0&
#2570
07
b0 C
b101 ?
1)
b11 5
1&
#2580
0&
#2590
b101 0
0)
b0 5
b1 C
1&
#2600
0&
#2610
b10 C
b1 5
1&
#2620
0&
#2630
b10 5
17
b11 C
1&
#2640
0&
#2650
07
b0 C
b10 A
1!
1)
b11 5
1&
#2660
0&
#2670
1#
b10 3
0)
b0 5
b1 C
1&
#2680
0&
#2690
b10 C
b1 5
1&
#2700
0&
#2710
b10 5
17
b11 C
1&
#2720
0&
#2730
07
b0 C
0@
b0 A
1)
b11 5
1&
#2740
0&
#2750
02
0"
b0 3
0)
b0 5
0!
b0 ?
1@
b1 A
1&
#2760
0&
#2770
b1 C
b0 0
12
0#
1"
b1 3
1&
#2780
0&
#2790
b1 5
b10 C
1&
#2800
0&
#2810
17
b11 C
b10 5
1&
#2820
0&
#2830
1)
b11 5
b1 ?
07
b0 C
1&
#2840
0&
#2850
b1 C
0)
b0 5
b1 0
1&
#2860
0&
#2870
b1 5
b10 C
1&
#2880
0&
#2890
17
b11 C
b10 5
1&
#2900
0&
#2910
1)
b11 5
b10 ?
07
b0 C
1&
#2920
0&
#2930
b1 C
0)
b0 5
b10 0
1&
#2940
0&
#2950
b1 5
b10 C
1&
#2960
0&
#2970
17
b11 C
b10 5
1&
#2980
0&
#2990
1)
b11 5
b11 ?
07
b0 C
1&
